feiyan/__init__.py
feiyan/client.py
feiyan/fy_client.py
feiyan/auth/__init__.py
feiyan/auth/md5_tool.py
feiyan/auth/sha_hmac256.py
feiyan/auth/signature_composer.py
feiyan/auth/url_encoder.py
feiyan/common/__init__.py
feiyan/common/constant.py
feiyan/http/__init__.py
feiyan/http/api.py
feiyan/http/fy_request.py
feiyan/http/request.py
feiyan/util/DateUtil.py
feiyan/util/ParamUtil.py
feiyan/util/UUIDUtil.py
feiyan/util/__init__.py
feiyan-1.0.7.dist-info/METADATA
feiyan-1.0.7.dist-info/RECORD
feiyan-1.0.7.dist-info/WHEEL
feiyan-1.0.7.dist-info/top_level.txt
