Metadata-Version: 2.1
Name: feiyan
Version: 1.0.7
Summary: iot feiyan package
Home-page: https://github.com/jerrygaoyang/feiyan
Author: jerrygaoyang
Author-email: 917616767@qq.com
License: UNKNOWN
Platform: UNKNOWN
Requires-Dist: requests
